hardpotato/__init__.py
hardpotato/chi1205b.py
hardpotato/chi1242b.py
hardpotato/chi601e.py
hardpotato/chi760e.py
hardpotato/emstatpico.py
hardpotato/load_data.py
hardpotato/pico_instrument.py
hardpotato/pico_mscript.py
hardpotato/pico_serial.py
hardpotato/potentiostat.py
hardpotato/save_data.py
hardpotato/test.py
hardpotato-1.3.13.dist-info/LICENSE
hardpotato-1.3.13.dist-info/METADATA
hardpotato-1.3.13.dist-info/WHEEL
hardpotato-1.3.13.dist-info/top_level.txt
hardpotato-1.3.13.dist-info/RECORD
