Metadata-Version: 2.1
Name: hardpotato
Version: 1.3.13
Summary: Python API to control programmable potentiostats.
Home-page: https://github.com/jrlLAB/hardpotato
Author: Oliver Rodriguez
Author-email: oliver.rdz@softpotato.xyz
Keywords: Electrochemistry
License-File: LICENSE
Requires-Dist: numpy
Requires-Dist: scipy
Requires-Dist: matplotlib
Requires-Dist: softpotato
Requires-Dist: pyserial
